dengsurvab/__init__.py
dengsurvab/alerts.py
dengsurvab/analytics.py
dengsurvab/auth.py
dengsurvab/cli.py
dengsurvab/client.py
dengsurvab/exceptions.py
dengsurvab/export.py
dengsurvab/models.py
dengsurvap_bf-0.1.0.dist-info/licenses/LICENSE
dengsurvap_bf-0.1.0.dist-info/METADATA
dengsurvap_bf-0.1.0.dist-info/WHEEL
dengsurvap_bf-0.1.0.dist-info/entry_points.txt
dengsurvap_bf-0.1.0.dist-info/top_level.txt
dengsurvap_bf-0.1.0.dist-info/RECORD
