Metadata-Version: 2.4
Name: dengsurvap-bf
Version: 0.1.0
Summary: Client Python pour l'API de surveillance de la dengue
Home-page: https://github.com/yamsaid/dengsurvap-bf
Author: Saïdou YAMEOGO - Data Analyst
Author-email: Saïdou YAMEOGO - Data Analyst <saidouyameogo3@gmail.com>
Maintainer-email: Équipe de développement Appi <saidouyameogo3@gmail.com>
License: MIT
Project-URL: Homepage, https://github.com/yamsaid/dengsurvap-bf
Project-URL: Documentation, https://dengsurvap-bf.readthedocs.io/
Project-URL: Repository, https://github.com/yamsaid/dengsurvap-bf
Project-URL: Bug Tracker, https://github.com/yamsaid/dengsurvap-bf/issues
Keywords: dengue,epidemiology,surveillance,health,api,client
Classifier: Development Status :: 3 - Alpha
Classifier: Intended Audience :: Developers
Classifier: Intended Audience :: Science/Research
Classifier: License :: OSI Approved :: MIT License
Classifier: Operating System :: OS Independent
Classifier: Programming Language :: Python :: 3
Classifier: Programming Language :: Python :: 3.8
Classifier: Programming Language :: Python :: 3.9
Classifier: Programming Language :: Python :: 3.10
Classifier: Programming Language :: Python :: 3.11
Classifier: Topic :: Scientific/Engineering :: Information Analysis
Classifier: Topic :: Software Development :: Libraries :: Python Modules
Requires-Python: >=3.8
License-File: LICENSE
Requires-Dist: requests>=2.25.0
Requires-Dist: pandas>=1.3.0
Requires-Dist: pydantic>=2.0.0
Requires-Dist: python-dateutil>=2.8.0
Requires-Dist: openpyxl>=3.0.0
Requires-Dist: PyJWT>=2.0.0
Requires-Dist: cryptography>=3.0.0
Requires-Dist: scikit-learn>=1.0.0
Provides-Extra: dev
Requires-Dist: pytest>=6.0; extra == "dev"
Requires-Dist: pytest-cov>=2.0; extra == "dev"
Requires-Dist: pytest-mock>=3.0; extra == "dev"
Requires-Dist: black>=21.0; extra == "dev"
Requires-Dist: flake8>=3.8; extra == "dev"
Requires-Dist: mypy>=0.900; extra == "dev"
Requires-Dist: pre-commit>=2.0; extra == "dev"
Requires-Dist: responses>=0.23.0; extra == "dev"
Provides-Extra: docs
Requires-Dist: sphinx>=4.0; extra == "docs"
Requires-Dist: sphinx-rtd-theme>=1.0; extra == "docs"
Requires-Dist: myst-parser>=0.15; extra == "docs"
Provides-Extra: analysis
Requires-Dist: numpy>=1.20.0; extra == "analysis"
Requires-Dist: scipy>=1.7.0; extra == "analysis"
Requires-Dist: matplotlib>=3.3.0; extra == "analysis"
Requires-Dist: seaborn>=0.11.0; extra == "analysis"
Requires-Dist: plotly>=5.0.0; extra == "analysis"
Requires-Dist: scikit-learn>=1.0.0; extra == "analysis"
Dynamic: author
Dynamic: home-page
Dynamic: license-file
Dynamic: requires-python
